alfort_dom/__init__.py
alfort_dom/app.py
alfort_dom/dom.py
alfort_dom/event.py
alfort_dom/local_storage.py
alfort_dom/location.py
alfort_dom/py.typed
alfort_dom-0.1.3.dist-info/LICENSE
alfort_dom-0.1.3.dist-info/WHEEL
alfort_dom-0.1.3.dist-info/METADATA
alfort_dom-0.1.3.dist-info/RECORD
