Metadata-Version: 2.1
Name: alfort-dom
Version: 0.1.3
Summary: A simple Elm like web application framework
Home-page: https://github.com/ar90n/alfort-dom
License: Apache-2.0
Keywords: declarative-ui,elm-architecture
Author: Masahiro Wada
Author-email: argon.argon.argon@gmail.com
Requires-Python: >=3.10,<4.0
Classifier: License :: OSI Approved :: Apache Software License
Classifier: Programming Language :: Python :: 3
Classifier: Programming Language :: Python :: 3.10
Classifier: Programming Language :: Python :: 3.11
Requires-Dist: alfort (>=0.1.9,<0.2.0)
Project-URL: Repository, https://github.com/ar90n/alfort-dom
